nokia/__init__.py
nokia-1.1.0.data/scripts/nokia
nokia-1.1.0.dist-info/LICENSE
nokia-1.1.0.dist-info/METADATA
nokia-1.1.0.dist-info/WHEEL
nokia-1.1.0.dist-info/top_level.txt
nokia-1.1.0.dist-info/zip-safe
nokia-1.1.0.dist-info/RECORD
