Metadata-Version: 2.1
Name: nokia
Version: 1.1.0
Summary: Library for the Nokia Health API
Home-page: https://github.com/orcasgit/python-nokia
Author: ORCAS
Author-email: developer@orcasinc.com
License: MIT License
Keywords: withings nokia
Platform: UNKNOWN
Classifier: Development Status :: 3 - Alpha
Classifier: Intended Audience :: Developers
Classifier: Programming Language :: Python
Classifier: Programming Language :: Python :: 2
Classifier: Programming Language :: Python :: 2.7
Classifier: Programming Language :: Python :: 3
Classifier: Programming Language :: Python :: 3.4
Classifier: Programming Language :: Python :: 3.5
Classifier: Programming Language :: Python :: 3.6
Classifier: Programming Language :: Python :: 3.7
Classifier: Programming Language :: Python :: Implementation
Classifier: Programming Language :: Python :: Implementation :: CPython
Classifier: Programming Language :: Python :: Implementation :: PyPy
Requires-Dist: arrow (<0.13,>=0.12)
Requires-Dist: cherrypy (<17.4,>=17.3)
Requires-Dist: requests (<2.20,>=2.19)
Requires-Dist: requests-oauth (<0.5,>=0.4.1)
Requires-Dist: requests-oauthlib (<1.1,>=1.0)
